datamesh/__init__.py
datamesh/contract/__init__.py
datamesh/contract/validator.py
datamesh/resources/odcs-json-schema.json
DataMesh-0.1.2.dist-info/LICENSE
DataMesh-0.1.2.dist-info/METADATA
DataMesh-0.1.2.dist-info/WHEEL
DataMesh-0.1.2.dist-info/entry_points.txt
DataMesh-0.1.2.dist-info/top_level.txt
DataMesh-0.1.2.dist-info/RECORD
